example_pkg_leon/__init__.py
example_pkg_leon/example_pkg_leon.py
example_pkg_leon-0.0.1.dist-info/METADATA
example_pkg_leon-0.0.1.dist-info/RECORD
example_pkg_leon-0.0.1.dist-info/WHEEL
example_pkg_leon-0.0.1.dist-info/top_level.txt
