Metadata-Version: 2.1
Name: example-pkg-leon
Version: 0.0.1
Summary: test project
Home-page: https://github.com/pypa/example-project
Author: Aumit Loen
Author-email: aumitleon1@gmail.com
License: UNKNOWN
Platform: UNKNOWN
Classifier: Programming Language :: Python :: 2
Classifier: License :: OSI Approved :: MIT License
Classifier: Operating System :: OS Independent
